nardis/__init__.py
nardis/asgi.py
nardis/constants.py
nardis/utils.py
nardis/http/__init__.py
nardis/http/request.py
nardis/http/response.py
nardis/http/utils.py
nardis/routing/__init__.py
nardis/routing/defaults.py
nardis/routing/matchers.py
nardis/routing/pattern.py
nardis-0.0.7.dist-info/METADATA
nardis-0.0.7.dist-info/RECORD
nardis-0.0.7.dist-info/WHEEL
nardis-0.0.7.dist-info/top_level.txt
