Metadata-Version: 2.1
Name: nardis
Version: 0.0.7
Summary: A web framework based on ASGI
Home-page: https://github.com/yoongkang/nardis
Author: Yoong Kang Lim
Author-email: yoongkang.lim@gmail.com
License: MIT
Platform: UNKNOWN
Classifier: License :: OSI Approved :: MIT License
Classifier: Programming Language :: Python
Classifier: Programming Language :: Python :: 3
Classifier: Programming Language :: Python :: 3.6
Classifier: Programming Language :: Python :: Implementation :: CPython
Classifier: Programming Language :: Python :: Implementation :: PyPy
Requires-Python: >=3.6
Requires-Dist: typing-extensions
Requires-Dist: uvicorn
